{
  "resourceType" : "ValueSet",
  "id" : "2.16.840.1.113762.1.4.1222.1053",
  "meta" : {
    "versionId" : "17",
    "lastUpdated" : "2024-09-12T22:37:08.000-04:00",
    "profile" : [
      "http://hl7.org/fhir/StructureDefinition/shareablevalueset",
      "http://hl7.org/fhir/us/cqfmeasures/StructureDefinition/computable-valueset-cqfm",
      "http://hl7.org/fhir/us/cqfmeasures/StructureDefinition/publishable-valueset-cqfm"
    ]
  },
  "extension" : [
    {
      "url" : "http://hl7.org/fhir/StructureDefinition/valueset-author",
      "valueContactDetail" : {
        "name" : "MCC eCare Plan Author"
      }
    },
    {
      "url" : "http://hl7.org/fhir/StructureDefinition/valueset-keyWord",
      "valueString" : "MCC_IG"
    },
    {
      "url" : "http://hl7.org/fhir/StructureDefinition/resource-lastReviewDate",
      "valueDate" : "2024-07-24"
    },
    {
      "url" : "http://hl7.org/fhir/StructureDefinition/valueset-effectiveDate",
      "valueDate" : "2023-07-20"
    }
  ],
  "url" : "http://cts.nlm.nih.gov/fhir/ValueSet/2.16.840.1.113762.1.4.1222.1053",
  "identifier" : [
    {
      "system" : "urn:ietf:rfc:3986",
      "value" : "urn:oid:2.16.840.1.113762.1.4.1222.1053"
    }
  ],
  "version" : "20230720",
  "name" : "IncomeLevel",
  "title" : "Income Level",
  "status" : "active",
  "date" : "2023-07-20T01:01:20-04:00",
  "publisher" : "HL7 Patient Care WG Steward",
  "jurisdiction" : [
    {
      "coding" : [
        {
          "system" : "urn:iso:std:iso:3166",
          "code" : "US"
        }
      ]
    }
  ],
  "purpose" : "(Clinical Focus: This set of values addresses terms representing \n questions intended to capture observations of individual or household income level.),(Data Element Scope: The intent of this set of values is to identify patients who have answered questions intended to capture observations of individual or household income level.),(Inclusion Criteria: Includes LOINC codes reflecting questions about  income.),(Exclusion Criteria: Terms not representative of question terms that reflection income questions.)",
  "compose" : {
    "include" : [
      {
        "system" : "http://loinc.org",
        "version" : "2.78",
        "filter" : [
          {
            "property" : "concept",
            "op" : "in",
            "value" : "77244-2,63509-4,63507-8,91570-2,63508-6,89566-4,63506-0,74185-0,63586-2,63510-2"
          }
        ]
      }
    ]
  },
  "expansion" : {
    "identifier" : "urn:uuid:f46acd69-4754-41fb-8597-f9f3a63c69ab",
    "timestamp" : "2024-11-08T22:03:38-05:00",
    "total" : 10,
    "contains" : [
      {
        "system" : "http://loinc.org",
        "version" : "2.78",
        "code" : "63506-0",
        "display" : "Was your total family income from all sources less than 50,000 dollars or 50,000 dollars or more [PhenX]"
      },
      {
        "system" : "http://loinc.org",
        "version" : "2.78",
        "code" : "63507-8",
        "display" : "Was your total family income from all sources less than 35,000 dollars or 35,000 dollars or more [PhenX]"
      },
      {
        "system" : "http://loinc.org",
        "version" : "2.78",
        "code" : "63508-6",
        "display" : "Was your total family income from all sources less than poverty threshold or more [PhenX]"
      },
      {
        "system" : "http://loinc.org",
        "version" : "2.78",
        "code" : "63509-4",
        "display" : "Was your total family income from all sources less than 100,000 dollars or 100,000 dollars or more [PhenX]"
      },
      {
        "system" : "http://loinc.org",
        "version" : "2.78",
        "code" : "63510-2",
        "display" : "Was your total family income from all sources less than 75,000 dollars or 75,000 dollars or more [PhenX]"
      },
      {
        "system" : "http://loinc.org",
        "version" : "2.78",
        "code" : "63586-2",
        "display" : "What was your best estimate of the total income of all family members from all sources, before taxes, in last year [PhenX]"
      },
      {
        "system" : "http://loinc.org",
        "version" : "2.78",
        "code" : "74185-0",
        "display" : "Percent of U.S. Federal Poverty Level"
      },
      {
        "system" : "http://loinc.org",
        "version" : "2.78",
        "code" : "77244-2",
        "display" : "Total combined household income range in last year"
      },
      {
        "system" : "http://loinc.org",
        "version" : "2.78",
        "code" : "89566-4",
        "display" : "Income status [CUBS]"
      },
      {
        "system" : "http://loinc.org",
        "version" : "2.78",
        "code" : "91570-2",
        "display" : "Employment net income in past 30 days"
      }
    ]
  }
}
