{
  "resourceType": "ValueSet",
  "id": "2.16.840.1.113883.3.464.1003.1029",
  "meta": {
    "versionId": "14",
    "lastUpdated": "2022-02-01T01:02:25.000-05:00"
  },
  "url": "http://cts.nlm.nih.gov/fhir/ValueSet/2.16.840.1.113883.3.464.1003.1029",
  "version": "20220201",
  "name": "Unilateral Oophorectomy Left",
  "status": "active",
  "date": "2022-02-01T01:02:25-05:00",
  "publisher": "NCQA PHEMUR",
  "compose": {
    "include": [
      {
        "system": "http://snomed.info/sct",
        "version": "http://snomed.info/sct/731000124108/version/20220301",
        "concept": [
          {
            "code": "176915001",
            "display": "Left salpingo-oophorectomy (procedure)"
          },
          {
            "code": "302191001",
            "display": "Abdominal hysterectomy and left salpingo-oophorectomy (procedure)"
          },
          {
            "code": "302377002",
            "display": "Left oophorectomy (procedure)"
          },
          {
            "code": "608885003",
            "display": "Laparoscopic left oophorectomy (procedure)"
          },
          {
            "code": "608888001",
            "display": "Laparoscopic left salpingo-oophorectomy (procedure)"
          },
          {
            "code": "739669004",
            "display": "Supracervical hysterectomy with left salpingo-oophorectomy (procedure)"
          },
          {
            "code": "739671004",
            "display": "Total hysterectomy with left oophorectomy (procedure)"
          },
          {
            "code": "739673001",
            "display": "Total hysterectomy with left salpingo-oophorectomy (procedure)"
          }
        ]
      }
    ]
  }
}