{
  "resourceType" : "ValueSet",
  "id" : "2.16.840.1.113883.3.526.2.1630",
  "meta" : {
    "versionId" : "17",
    "lastUpdated" : "2021-01-15T13:05:12.000-05:00"
  },
  "url" : "http://cts.nlm.nih.gov/fhir/ValueSet/2.16.840.1.113883.3.526.2.1630",
  "version" : "20170504",
  "name" : "Chorioretinal Scars",
  "status" : "active",
  "date" : "2017-05-04T01:00:13-04:00",
  "publisher" : "American Academy of Ophthalmology Steward",
  "compose" : {
    "include" : [{
      "system" : "http://hl7.org/fhir/sid/icd-9-cm",
      "version" : "2013",
      "concept" : [{
        "code" : "363.30",
        "display" : "Chorioretinal scar, unspecified"
      },
      {
        "code" : "363.31",
        "display" : "Solar retinopathy"
      },
      {
        "code" : "363.32",
        "display" : "Other macular scars"
      },
      {
        "code" : "363.33",
        "display" : "Other scars of posterior pole"
      },
      {
        "code" : "363.35",
        "display" : "Disseminated scars"
      }]
    }]
  },
  "expansion" : {
    "identifier" : "urn:uuid:632e7bac-b845-4e33-b58c-facad27c2863",
    "timestamp" : "2022-09-27T18:59:00-04:00",
    "total" : 5,
    "offset" : 0,
    "parameter" : [{
      "name" : "count",
      "valueInteger" : 1000
    },
    {
      "name" : "offset",
      "valueInteger" : 0
    }],
    "contains" : [{
      "system" : "http://hl7.org/fhir/sid/icd-9-cm",
      "version" : "2013",
      "code" : "363.30",
      "display" : "Chorioretinal scar, unspecified"
    },
    {
      "system" : "http://hl7.org/fhir/sid/icd-9-cm",
      "version" : "2013",
      "code" : "363.31",
      "display" : "Solar retinopathy"
    },
    {
      "system" : "http://hl7.org/fhir/sid/icd-9-cm",
      "version" : "2013",
      "code" : "363.32",
      "display" : "Other macular scars"
    },
    {
      "system" : "http://hl7.org/fhir/sid/icd-9-cm",
      "version" : "2013",
      "code" : "363.33",
      "display" : "Other scars of posterior pole"
    },
    {
      "system" : "http://hl7.org/fhir/sid/icd-9-cm",
      "version" : "2013",
      "code" : "363.35",
      "display" : "Disseminated scars"
    }]
  }
}