{
  "resourceType" : "ValueSet",
  "id" : "2.16.840.1.113762.1.4.1146.2160",
  "meta" : {
    "versionId" : "6",
    "lastUpdated" : "2023-06-02T01:03:51.000-04:00",
    "profile" : [
      "http://hl7.org/fhir/StructureDefinition/shareablevalueset",
      "http://hl7.org/fhir/us/cqfmeasures/StructureDefinition/publishable-valueset-cqfm"
    ]
  },
  "extension" : [
    {
      "url" : "http://hl7.org/fhir/StructureDefinition/valueset-author",
      "valueString" : "CSTE Author"
    },
    {
      "url" : "http://hl7.org/fhir/StructureDefinition/valueset-keyWord",
      "valueString" : "Mpox,Trigger"
    },
    {
      "url" : "http://hl7.org/fhir/StructureDefinition/resource-lastReviewDate",
      "valueDate" : "2023-06-02"
    },
    {
      "url" : "http://hl7.org/fhir/StructureDefinition/valueset-effectiveDate",
      "valueDate" : "2023-06-02"
    }
  ],
  "url" : "http://cts.nlm.nih.gov/fhir/ValueSet/2.16.840.1.113762.1.4.1146.2160",
  "identifier" : [
    {
      "system" : "urn:ietf:rfc:3986",
      "value" : "urn:oid:2.16.840.1.113762.1.4.1146.2160"
    }
  ],
  "version" : "20230602",
  "name" : "OrthopoxTestPanelsForOrthopoxvirusNucleicAcid",
  "title" : "Orthopox (Test Panels for orthopoxvirus Nucleic Acid)",
  "status" : "active",
  "date" : "2023-06-02T01:03:51-04:00",
  "publisher" : "CSTE Steward",
  "jurisdiction" : [
    {
      "coding" : [
        {
          "system" : "urn:iso:std:iso:3166",
          "code" : "US"
        }
      ]
    }
  ],
  "purpose" : "(Clinical Focus: This set of values contains codes for laboratory test panel names associated with detecting the presence of orthopoxvirus Nucleic Acid),(Data Element Scope: Laboratory tests names that were ordered or observed),(Inclusion Criteria: orthopoxvirus Nucleic Acid panel),(Exclusion Criteria: None)",
  "compose" : {
    "include" : [
      {
        "system" : "http://loinc.org",
        "concept" : [
          {
            "code" : "101398-6",
            "display" : "Monkeypox virus and Orthopoxvirus.non-variola DNA panel - Specimen"
          }
        ]
      }
    ]
  },
  "expansion" : {
    "identifier" : "urn:uuid:5788958d-b3f5-4116-b0ee-cfbec4df20cb",
    "timestamp" : "2023-11-26T17:04:19-05:00",
    "total" : 1,
    "contains" : [
      {
        "system" : "http://loinc.org",
        "version" : "2.76",
        "code" : "101398-6",
        "display" : "Monkeypox virus and Orthopoxvirus.non-variola DNA panel - Specimen"
      }
    ]
  }
}
