{
  "resourceType": "ValueSet",
  "id": "2.16.840.1.113883.11.20.9.69.4",
  "meta": {
    "versionId": "11",
    "lastUpdated": "2022-02-28T12:07:59.000-05:00"
  },
  "url": "http://cts.nlm.nih.gov/fhir/ValueSet/2.16.840.1.113883.11.20.9.69.4",
  "version": "20200604",
  "name": "Advance Directives Categories",
  "status": "active",
  "date": "2020-06-04T01:00:20-04:00",
  "publisher": "ADVault",
  "compose": {
    "include": [
      {
        "system": "http://loinc.org",
        "version": "2.72",
        "concept": [
          {
            "code": "64298-3",
            "display": "Power of attorney"
          },
          {
            "code": "81334-5",
            "display": "Patient Personal advance care plan"
          },
          {
            "code": "86533-7",
            "display": "Patient Living will"
          },
          {
            "code": "92664-2",
            "display": "Power of attorney and Living will"
          }
        ]
      }
    ]
  },
  "expansion": {
    "identifier": "urn:uuid:cbda0935-96f2-408d-8521-cc7500671a73",
    "timestamp": "2022-09-27T17:25:01-04:00",
    "total": 4,
    "offset": 0,
    "parameter": [
      {
        "name": "count",
        "valueInteger": 1000
      },
      {
        "name": "offset",
        "valueInteger": 0
      }
    ],
    "contains": [
      {
        "system": "http://loinc.org",
        "version": "2.72",
        "code": "64298-3",
        "display": "Power of attorney"
      },
      {
        "system": "http://loinc.org",
        "version": "2.72",
        "code": "81334-5",
        "display": "Patient Personal advance care plan"
      },
      {
        "system": "http://loinc.org",
        "version": "2.72",
        "code": "86533-7",
        "display": "Patient Living will"
      },
      {
        "system": "http://loinc.org",
        "version": "2.72",
        "code": "92664-2",
        "display": "Power of attorney and Living will"
      }
    ]
  }
}