{"resourceType":"ValueSet","id":"2.16.840.1.113762.1.4.1116.528","meta":{"versionId":"5","lastUpdated":"2018-08-28T12:15:18.000-04:00"},"text":{"status":"generated","div":"<div xmlns=\"http://www.w3.org/1999/xhtml\">\n      <h2>Treatment Summary Report CPT</h2>\n      <p>This value set includes codes from the following code systems:</p>\n      <ul>\n        <li>Include these codes as defined in \n          <code>http://www.ama-assn.org/go/cpt</code>\n          <table class=\"none\">\n            <tr>\n              <td>\n                <b>Code</b>\n              </td>\n              <td>\n                <b>Display</b>\n              </td>\n            </tr>\n            <tr>\n              <td>5020F</td>\n              <td>Treatment summary report communicated to physician(s) or other qualified health care professional(s) managing continuing care and to the patient within 1 month of completing treatment (ONC)</td>\n              <td/>\n            </tr>\n          </table>\n        </li>\n      </ul>\n    </div>"},"url":"http://cts.nlm.nih.gov/fhir/ValueSet/2.16.840.1.113762.1.4.1116.528","version":"20180828","name":"Treatment Summary Report CPT","status":"active","date":"2018-08-28T01:00:01-04:00","publisher":"American Society of Clinical Oncology Steward","compose":{"include":[{"system":"http://www.ama-assn.org/go/cpt","concept":[{"code":"5020F","display":"Treatment summary report communicated to physician(s) or other qualified health care professional(s) managing continuing care and to the patient within 1 month of completing treatment (ONC)"}]}]}}