{
  "resourceType" : "ValueSet",
  "id" : "2.16.840.1.113762.1.4.1146.490",
  "meta" : {
    "versionId" : "17",
    "lastUpdated" : "2023-09-11T15:30:06.000-04:00",
    "profile" : [
      "http://hl7.org/fhir/StructureDefinition/shareablevalueset",
      "http://hl7.org/fhir/us/cqfmeasures/StructureDefinition/publishable-valueset-cqfm"
    ]
  },
  "extension" : [
    {
      "url" : "http://hl7.org/fhir/StructureDefinition/valueset-author",
      "valueString" : "CSTE Author"
    },
    {
      "url" : "http://hl7.org/fhir/StructureDefinition/valueset-keyWord",
      "valueString" : "Anaplasmosis,Not_Used"
    },
    {
      "url" : "http://hl7.org/fhir/StructureDefinition/resource-lastReviewDate",
      "valueDate" : "2022-12-15"
    },
    {
      "url" : "http://hl7.org/fhir/StructureDefinition/valueset-effectiveDate",
      "valueDate" : "2023-09-11"
    }
  ],
  "url" : "http://cts.nlm.nih.gov/fhir/ValueSet/2.16.840.1.113762.1.4.1146.490",
  "identifier" : [
    {
      "system" : "urn:ietf:rfc:3986",
      "value" : "urn:oid:2.16.840.1.113762.1.4.1146.490"
    }
  ],
  "version" : "20200513",
  "name" : "NU_AnaplasmosisTestsForAnaplasmaSpeciesIgMIgGAntibodyQuantitative",
  "title" : "NU_Anaplasmosis (Tests for Anaplasma species IgM IgG Antibody [Quantitative])",
  "status" : "active",
  "experimental" : false,
  "date" : "2020-05-13T01:00:22-04:00",
  "publisher" : "CSTE Steward",
  "jurisdiction" : [
    {
      "coding" : [
        {
          "system" : "urn:iso:std:iso:3166",
          "code" : "US"
        }
      ]
    }
  ],
  "purpose" : "(Clinical Focus: This set of values contains codes for laboratory test names associated with detecting the presence of Anaplasma species IgM or IgG Antibody .),(Data Element Scope: Laboratory tests names that were ordered or observed.),(Inclusion Criteria: component: Anaplasma IgG or IgM Antibody;\n\nLOINC search: LOINC search: ‘anaplasma (IgM OR IgG) Ab Scale:Qn  -panel’),(Exclusion Criteria: Panel tests; non-quantitative tests)",
  "compose" : {
    "include" : [
      {
        "system" : "http://loinc.org",
        "concept" : [
          {
            "code" : "16808-8",
            "display" : "Anaplasma phagocytophilum IgG Ab [Units/volume] in Serum"
          },
          {
            "code" : "16809-6",
            "display" : "Anaplasma phagocytophilum IgM Ab [Units/volume] in Serum"
          },
          {
            "code" : "23877-4",
            "display" : "Anaplasma phagocytophilum IgG Ab [Titer] in Serum by Immunofluorescence"
          },
          {
            "code" : "23878-2",
            "display" : "Anaplasma phagocytophilum IgM Ab [Titer] in Serum by Immunofluorescence"
          },
          {
            "code" : "32691-8",
            "display" : "Anaplasma phagocytophilum IgG Ab [Titer] in Serum"
          },
          {
            "code" : "32692-6",
            "display" : "Anaplasma phagocytophilum IgM Ab [Titer] in Serum"
          },
          {
            "code" : "48876-7",
            "display" : "Anaplasma phagocytophilum IgM Ab [Titer] in Body fluid by Immunofluorescence"
          },
          {
            "code" : "48877-5",
            "display" : "Anaplasma phagocytophilum IgG Ab [Titer] in Body fluid by Immunofluorescence"
          },
          {
            "code" : "49213-2",
            "display" : "Anaplasma phagocytophilum IgG Ab [Titer] in Body fluid"
          },
          {
            "code" : "49214-0",
            "display" : "Anaplasma phagocytophilum IgM Ab [Titer] in Body fluid"
          }
        ]
      }
    ]
  },
  "expansion" : {
    "identifier" : "urn:uuid:b9fb3f48-57c1-4fdc-8fd1-957c46835255",
    "timestamp" : "2023-11-26T17:09:19-05:00",
    "total" : 10,
    "contains" : [
      {
        "system" : "http://loinc.org",
        "version" : "2.76",
        "code" : "16808-8",
        "display" : "Anaplasma phagocytophilum IgG Ab [Units/volume] in Serum"
      },
      {
        "system" : "http://loinc.org",
        "version" : "2.76",
        "code" : "16809-6",
        "display" : "Anaplasma phagocytophilum IgM Ab [Units/volume] in Serum"
      },
      {
        "system" : "http://loinc.org",
        "version" : "2.76",
        "code" : "23877-4",
        "display" : "Anaplasma phagocytophilum IgG Ab [Titer] in Serum by Immunofluorescence"
      },
      {
        "system" : "http://loinc.org",
        "version" : "2.76",
        "code" : "23878-2",
        "display" : "Anaplasma phagocytophilum IgM Ab [Titer] in Serum by Immunofluorescence"
      },
      {
        "system" : "http://loinc.org",
        "version" : "2.76",
        "code" : "32691-8",
        "display" : "Anaplasma phagocytophilum IgG Ab [Titer] in Serum"
      },
      {
        "system" : "http://loinc.org",
        "version" : "2.76",
        "code" : "32692-6",
        "display" : "Anaplasma phagocytophilum IgM Ab [Titer] in Serum"
      },
      {
        "system" : "http://loinc.org",
        "version" : "2.76",
        "code" : "48876-7",
        "display" : "Anaplasma phagocytophilum IgM Ab [Titer] in Body fluid by Immunofluorescence"
      },
      {
        "system" : "http://loinc.org",
        "version" : "2.76",
        "code" : "48877-5",
        "display" : "Anaplasma phagocytophilum IgG Ab [Titer] in Body fluid by Immunofluorescence"
      },
      {
        "system" : "http://loinc.org",
        "version" : "2.76",
        "code" : "49213-2",
        "display" : "Anaplasma phagocytophilum IgG Ab [Titer] in Body fluid"
      },
      {
        "system" : "http://loinc.org",
        "version" : "2.76",
        "code" : "49214-0",
        "display" : "Anaplasma phagocytophilum IgM Ab [Titer] in Body fluid"
      }
    ]
  }
}
