<?xml version="1.0" encoding="UTF-8"?><SearchParameter xmlns="http://hl7.org/fhir"><id value="Library-date"/><url value="http://hl7.org/fhir/SearchParameter/Library-date"/><name value="date"/><status value="draft"/><experimental value="false"/><date value="2019-10-24T11:53:00+11:00"/><publisher value="Health Level Seven International (Clinical Decision Support)"/><contact><telecom><system value="url"/><value value="http://hl7.org/fhir"/></telecom></contact><contact><telecom><system value="url"/><value value="http://www.hl7.org/Special/committees/dss/index.cfm"/></telecom></contact><code value="date"/><base value="Library"/><type value="date"/><description value="The library publication date"/><expression value="Library.date"/><xpath value="f:Library/f:date"/><xpathUsage value="normal"/></SearchParameter>