<?xml version="1.0" encoding="UTF-8"?><SearchParameter xmlns="http://hl7.org/fhir"><id value="SupplyDelivery-supplier"/><extension url="http://hl7.org/fhir/StructureDefinition/structuredefinition-standards-status"><valueCode value="trial-use"/></extension><url value="http://hl7.org/fhir/SearchParameter/SupplyDelivery-supplier"/><version value="4.0.1"/><name value="supplier"/><status value="draft"/><experimental value="false"/><date value="2019-10-30T13:56:25+11:00"/><publisher value="Health Level Seven International (Orders and Observations)"/><contact><telecom><system value="url"/><value value="http://hl7.org/fhir"/></telecom></contact><contact><telecom><system value="url"/><value value="http://www.hl7.org/Special/committees/orders/index.cfm"/></telecom></contact><description value="Dispenser"/><code value="supplier"/><base value="SupplyDelivery"/><type value="reference"/><expression value="SupplyDelivery.supplier"/><xpath value="f:SupplyDelivery/f:supplier"/><xpathUsage value="normal"/><target value="Practitioner"/><target value="Organization"/><target value="PractitionerRole"/></SearchParameter>