{"resourceType":"CodeSystem","id":"v2-0434","meta":{"profile":["http://hl7.org/fhir/StructureDefinition/valueset-shareable-definition"]},"text":{"status":"additional","div":"<div xmlns=\"http://www.w3.org/1999/xhtml\">\n\t\t\t\t\t\t<p>Patient Condition Code</p>\n\t\t\t\t\t\t<table class=\"grid\">\n\t\t\t\t\t\t\t<tr>\n\t\t\t\t\t\t\t\t<td>\n\t\t\t\t\t\t\t\t\t<b>Code</b>\n\t\t\t\t\t\t\t\t</td>\n\t\t\t\t\t\t\t\t<td>\n\t\t\t\t\t\t\t\t\t<b>Description</b>\n\t\t\t\t\t\t\t\t</td>\n\t\t\t\t\t\t\t\t<td>\n\t\t\t\t\t\t\t\t\t<b>Deutsch (German)</b>\n\t\t\t\t\t\t\t\t</td>\n\t\t\t\t\t\t\t\t<td>\n\t\t\t\t\t\t\t\t\t<b>Nederlands (Dutch)</b>\n\t\t\t\t\t\t\t\t</td>\n\t\t\t\t\t\t\t\t<td>\n\t\t\t\t\t\t\t\t\t<b>Comment</b>\n\t\t\t\t\t\t\t\t</td>\n\t\t\t\t\t\t\t\t<td>\n\t\t\t\t\t\t\t\t\t<b>Version</b>\n\t\t\t\t\t\t\t\t</td>\n\t\t\t\t\t\t\t</tr>\n\t\t\t\t\t\t\t<tr>\n\t\t\t\t\t\t\t\t<td>a\n                  <a name=\"a\"> </a>\n\t\t\t\t\t\t\t\t</td>\n\t\t\t\t\t\t\t\t<td>Satisfactory</td>\n\t\t\t\t\t\t\t\t<td>zufriedenstellend</td>\n\t\t\t\t\t\t\t\t<td/>\n\t\t\t\t\t\t\t\t<td/>\n\t\t\t\t\t\t\t\t<td>added v2.4</td>\n\t\t\t\t\t\t\t</tr>\n\t\t\t\t\t\t\t<tr>\n\t\t\t\t\t\t\t\t<td>c\n                  <a name=\"c\"> </a>\n\t\t\t\t\t\t\t\t</td>\n\t\t\t\t\t\t\t\t<td>Critical</td>\n\t\t\t\t\t\t\t\t<td>kritisch</td>\n\t\t\t\t\t\t\t\t<td/>\n\t\t\t\t\t\t\t\t<td/>\n\t\t\t\t\t\t\t\t<td>added v2.4</td>\n\t\t\t\t\t\t\t</tr>\n\t\t\t\t\t\t\t<tr>\n\t\t\t\t\t\t\t\t<td>o\n                  <a name=\"o\"> </a>\n\t\t\t\t\t\t\t\t</td>\n\t\t\t\t\t\t\t\t<td>Other</td>\n\t\t\t\t\t\t\t\t<td>sonstiges</td>\n\t\t\t\t\t\t\t\t<td>Anders</td>\n\t\t\t\t\t\t\t\t<td/>\n\t\t\t\t\t\t\t\t<td>added v2.4</td>\n\t\t\t\t\t\t\t</tr>\n\t\t\t\t\t\t\t<tr>\n\t\t\t\t\t\t\t\t<td>p\n                  <a name=\"p\"> </a>\n\t\t\t\t\t\t\t\t</td>\n\t\t\t\t\t\t\t\t<td>Poor</td>\n\t\t\t\t\t\t\t\t<td>schlecht</td>\n\t\t\t\t\t\t\t\t<td/>\n\t\t\t\t\t\t\t\t<td/>\n\t\t\t\t\t\t\t\t<td>added v2.4</td>\n\t\t\t\t\t\t\t</tr>\n\t\t\t\t\t\t\t<tr>\n\t\t\t\t\t\t\t\t<td>s\n                  <a name=\"s\"> </a>\n\t\t\t\t\t\t\t\t</td>\n\t\t\t\t\t\t\t\t<td>Stable</td>\n\t\t\t\t\t\t\t\t<td>stabil</td>\n\t\t\t\t\t\t\t\t<td/>\n\t\t\t\t\t\t\t\t<td/>\n\t\t\t\t\t\t\t\t<td>added v2.4</td>\n\t\t\t\t\t\t\t</tr>\n\t\t\t\t\t\t\t<tr>\n\t\t\t\t\t\t\t\t<td>u\n                  <a name=\"u\"> </a>\n\t\t\t\t\t\t\t\t</td>\n\t\t\t\t\t\t\t\t<td>Unknown</td>\n\t\t\t\t\t\t\t\t<td>unbekannt</td>\n\t\t\t\t\t\t\t\t<td>Onbekend</td>\n\t\t\t\t\t\t\t\t<td/>\n\t\t\t\t\t\t\t\t<td>added v2.4</td>\n\t\t\t\t\t\t\t</tr>\n\t\t\t\t\t\t</table>\n\t\t\t\t\t</div>"},"extension":[{"url":"http://hl7.org/fhir/StructureDefinition/valueset-oid","valueUri":"urn:oid:2.16.840.1.133883.18.275"}],"url":"http://hl7.org/fhir/v2/0434","version":"2.8.2","name":"v2 Patient Condition Code","status":"active","experimental":true,"publisher":"HL7, Inc","contact":[{"telecom":[{"system":"other","value":"http://hl7.org","rank":1}]}],"description":"FHIR Value set/code system definition for HL7 v2 table 0434 ( Patient Condition Code)","caseSensitive":false,"valueSet":"http://hl7.org/fhir/ValueSet/v2-0434","compositional":false,"versionNeeded":false,"content":"complete","count":0,"concept":[{"code":"A","display":"Satisfactory","designation":[{"language":"de","use":{"userSelected":false},"value":"zufriedenstellend"}]},{"code":"C","display":"Critical","designation":[{"language":"de","use":{"userSelected":false},"value":"kritisch"}]},{"code":"O","display":"Other","designation":[{"language":"de","use":{"userSelected":false},"value":"sonstiges"},{"language":"nl","use":{"userSelected":false},"value":"Anders"}]},{"code":"P","display":"Poor","designation":[{"language":"de","use":{"userSelected":false},"value":"schlecht"}]},{"code":"S","display":"Stable","designation":[{"language":"de","use":{"userSelected":false},"value":"stabil"}]},{"code":"U","display":"Unknown","designation":[{"language":"de","use":{"userSelected":false},"value":"unbekannt"},{"language":"nl","use":{"userSelected":false},"value":"Onbekend"}]}]}