<?xml version="1.0" encoding="UTF-8"?><SearchParameter xmlns="http://hl7.org/fhir"><id value="SupplyDelivery-status"/><extension url="http://hl7.org/fhir/StructureDefinition/structuredefinition-standards-status"><valueCode value="trial-use"/></extension><url value="http://hl7.org/fhir/SearchParameter/SupplyDelivery-status"/><version value="4.3.0"/><name value="status"/><status value="draft"/><experimental value="false"/><date value="2022-05-28T12:47:40+10:00"/><publisher value="Health Level Seven International (Orders and Observations)"/><contact><telecom><system value="url"/><value value="http://hl7.org/fhir"/></telecom></contact><contact><telecom><system value="url"/><value value="http://www.hl7.org/Special/committees/orders/index.cfm"/></telecom></contact><description value="in-progress | completed | abandoned | entered-in-error"/><code value="status"/><base value="SupplyDelivery"/><type value="token"/><expression value="SupplyDelivery.status"/><xpath value="f:SupplyDelivery/f:status"/><xpathUsage value="normal"/></SearchParameter>