<?xml version="1.0" encoding="UTF-8"?><SearchParameter xmlns="http://hl7.org/fhir"><id value="TestScript-context-quantity"/><extension url="http://hl7.org/fhir/StructureDefinition/structuredefinition-standards-status"><valueCode value="trial-use"/></extension><url value="http://hl7.org/fhir/SearchParameter/TestScript-context-quantity"/><version value="4.3.0"/><name value="context-quantity"/><status value="draft"/><experimental value="false"/><date value="2022-05-28T12:47:40+10:00"/><publisher value="Health Level Seven International (FHIR Infrastructure)"/><contact><telecom><system value="url"/><value value="http://hl7.org/fhir"/></telecom></contact><contact><telecom><system value="url"/><value value="http://www.hl7.org/Special/committees/fiwg/index.cfm"/></telecom></contact><description value="A quantity- or range-valued use context assigned to the test script"/><code value="context-quantity"/><base value="TestScript"/><type value="quantity"/><expression value="(TestScript.useContext.value as Quantity) | (TestScript.useContext.value as Range)"/><xpath value="f:TestScript/f:useContext/f:valueQuantity | f:TestScript/f:useContext/f:valueRange"/><xpathUsage value="normal"/><comparator value="eq"/><comparator value="ne"/><comparator value="gt"/><comparator value="ge"/><comparator value="lt"/><comparator value="le"/><comparator value="sa"/><comparator value="eb"/><comparator value="ap"/></SearchParameter>