<?xml version="1.0" encoding="UTF-8"?><SearchParameter xmlns="http://hl7.org/fhir"><id value="MedicationAdministration-context"/><extension url="http://hl7.org/fhir/StructureDefinition/structuredefinition-standards-status"><valueCode value="trial-use"/></extension><url value="http://hl7.org/fhir/SearchParameter/MedicationAdministration-context"/><version value="4.3.0"/><name value="context"/><status value="draft"/><experimental value="false"/><date value="2022-05-28T12:47:40+10:00"/><publisher value="Health Level Seven International (Pharmacy)"/><contact><telecom><system value="url"/><value value="http://hl7.org/fhir"/></telecom></contact><contact><telecom><system value="url"/><value value="http://www.hl7.org/Special/committees/medication/index.cfm"/></telecom></contact><description value="Return administrations that share this encounter or episode of care"/><code value="context"/><base value="MedicationAdministration"/><type value="reference"/><expression value="MedicationAdministration.context"/><xpath value="f:MedicationAdministration/f:context"/><xpathUsage value="normal"/><target value="EpisodeOfCare"/><target value="Encounter"/></SearchParameter>